floris/__init__.py
floris/convert_floris_input_v3_to_v4.py
floris/convert_turbine_v3_to_v4.py
floris/cut_plane.py
floris/default_inputs.yaml
floris/floris_model.py
floris/flow_visualization.py
floris/heterogeneous_map.py
floris/layout_visualization.py
floris/logging_manager.py
floris/par_floris_model.py
floris/parallel_floris_model.py
floris/type_dec.py
floris/uncertain_floris_model.py
floris/utilities.py
floris/wind_data.py
floris/core/__init__.py
floris/core/base.py
floris/core/core.py
floris/core/farm.py
floris/core/flow_field.py
floris/core/grid.py
floris/core/rotor_velocity.py
floris/core/solver.py
floris/core/wake.py
floris/core/turbine/__init__.py
floris/core/turbine/controller_dependent_operation_model.py
floris/core/turbine/operation_models.py
floris/core/turbine/turbine.py
floris/core/turbine/unified_momentum_model.py
floris/core/wake_combination/__init__.py
floris/core/wake_combination/fls.py
floris/core/wake_combination/max.py
floris/core/wake_combination/sosfs.py
floris/core/wake_deflection/__init__.py
floris/core/wake_deflection/empirical_gauss.py
floris/core/wake_deflection/gauss.py
floris/core/wake_deflection/jimenez.py
floris/core/wake_deflection/none.py
floris/core/wake_turbulence/__init__.py
floris/core/wake_turbulence/crespo_hernandez.py
floris/core/wake_turbulence/none.py
floris/core/wake_turbulence/wake_induced_mixing.py
floris/core/wake_velocity/__init__.py
floris/core/wake_velocity/cumulative_gauss_curl.py
floris/core/wake_velocity/empirical_gauss.py
floris/core/wake_velocity/gauss.py
floris/core/wake_velocity/jensen.py
floris/core/wake_velocity/none.py
floris/core/wake_velocity/turbopark.py
floris/core/wake_velocity/turbopark_lookup_table.mat
floris/core/wake_velocity/turboparkgauss.py
floris/optimization/__init__.py
floris/optimization/layout_optimization/__init__.py
floris/optimization/layout_optimization/layout_optimization_base.py
floris/optimization/layout_optimization/layout_optimization_boundary_grid.py
floris-4.5.1.dist-info/licenses/LICENSE.txt
floris-4.5.1.dist-info/METADATA
floris-4.5.1.dist-info/WHEEL
floris-4.5.1.dist-info/top_level.txt
floris-4.5.1.dist-info/RECORD
