Metadata-Version: 2.4
Name: floris
Version: 4.5.1
Summary: A controls-oriented engineering wake model.
Author-email: Rafael Mudafort <Rafael.Mudafort@nrel.gov>, Paul Fleming <Paul.Fleming@nrel.gov>, "Michael (Misha) Sinner" <Michael.Sinner@nrel.gov>, Eric Simley <Eric.Simley@nrel.gov>, Christopher Bay <Christopher.Bay@nrel.gov>
License: BSD 3-Clause License
Project-URL: Homepage, https://github.com/NREL/floris
Project-URL: Documentation, https://nrel.github.io/floris/
Keywords: floris
Classifier: License :: OSI Approved :: BSD License
Classifier: Programming Language :: Python
Classifier: Programming Language :: Python :: 3
Classifier: Programming Language :: Python :: 3.9
Classifier: Programming Language :: Python :: 3.10
Classifier: Programming Language :: Python :: 3.11
Classifier: Programming Language :: Python :: 3.12
Classifier: Programming Language :: Python :: 3.13
Classifier: Programming Language :: Python :: Implementation :: CPython
Classifier: Programming Language :: Python :: Implementation :: PyPy
Requires-Python: >=3.9
License-File: LICENSE.txt
Requires-Dist: attrs
Requires-Dist: pyyaml~=6.0
Requires-Dist: numexpr~=2.0
Requires-Dist: numpy~=2.0
Requires-Dist: scipy~=1.1
Requires-Dist: matplotlib~=3.0
Requires-Dist: pandas~=2.0
Requires-Dist: shapely~=2.0
Requires-Dist: coloredlogs~=15.0
Requires-Dist: pathos~=0.3
Provides-Extra: docs
Requires-Dist: jupyter-book~=1.0; extra == "docs"
Requires-Dist: sphinx-book-theme~=1.0; extra == "docs"
Requires-Dist: sphinx-autodoc-typehints~=2.0; extra == "docs"
Requires-Dist: sphinxcontrib-autoyaml~=1.0; extra == "docs"
Requires-Dist: sphinxcontrib.mermaid~=1.0; extra == "docs"
Requires-Dist: bokeh~=3.7; extra == "docs"
Provides-Extra: develop
Requires-Dist: pytest~=8.0; extra == "develop"
Requires-Dist: pytest-benchmark~=5.1; extra == "develop"
Requires-Dist: pre-commit~=4.0; extra == "develop"
Requires-Dist: ruff~=0.9; extra == "develop"
Requires-Dist: isort~=5.0; extra == "develop"
Dynamic: license-file
